<?xml version="1.0" encoding="UTF-8"?>
<DEFECTS>
  <DEFECT>
    <SFA>
      <FILEPATH>e:\qqdownload\ls\edf-tools-master\simple_edf_mission_parser</FILEPATH>
      <FILENAME>modmanager.cpp</FILENAME>
      <LINE>31</LINE>
      <COLUMN>48</COLUMN>
    </SFA>
    <DEFECTCODE>6276</DEFECTCODE>
    <DESCRIPTION>语义不同的字符串类型之间的强制转换: char * 转换为 wchar_t *。使用无效的字符串会导致未定义的行为。</DESCRIPTION>
    <FUNCTION>CWpnListMgr::HandleWindow</FUNCTION>
    <DECORATED>?HandleWindow@CWpnListMgr@@QAGJPAUHWND__@@IIJ@Z</DECORATED>
    <FUNCLINE>22</FUNCLINE>
    <PATH></PATH>
  </DEFECT>
  <DEFECT>
    <SFA>
      <FILEPATH>e:\qqdownload\ls\edf-tools-master\simple_edf_mission_parser</FILEPATH>
      <FILENAME>modmanager.cpp</FILENAME>
      <LINE>32</LINE>
      <COLUMN>48</COLUMN>
    </SFA>
    <DEFECTCODE>6276</DEFECTCODE>
    <DESCRIPTION>语义不同的字符串类型之间的强制转换: char * 转换为 wchar_t *。使用无效的字符串会导致未定义的行为。</DESCRIPTION>
    <FUNCTION>CWpnListMgr::HandleWindow</FUNCTION>
    <DECORATED>?HandleWindow@CWpnListMgr@@QAGJPAUHWND__@@IIJ@Z</DECORATED>
    <FUNCLINE>22</FUNCLINE>
    <PATH></PATH>
  </DEFECT>
  <DEFECT>
    <SFA>
      <FILEPATH>e:\qqdownload\ls\edf-tools-master\simple_edf_mission_parser</FILEPATH>
      <FILENAME>modmanager.cpp</FILENAME>
      <LINE>33</LINE>
      <COLUMN>66</COLUMN>
    </SFA>
    <DEFECTCODE>6276</DEFECTCODE>
    <DESCRIPTION>语义不同的字符串类型之间的强制转换: char * 转换为 wchar_t *。使用无效的字符串会导致未定义的行为。</DESCRIPTION>
    <FUNCTION>CWpnListMgr::HandleWindow</FUNCTION>
    <DECORATED>?HandleWindow@CWpnListMgr@@QAGJPAUHWND__@@IIJ@Z</DECORATED>
    <FUNCLINE>22</FUNCLINE>
    <PATH></PATH>
  </DEFECT>
  <DEFECT>
    <SFA>
      <FILEPATH>e:\qqdownload\ls\edf-tools-master\simple_edf_mission_parser</FILEPATH>
      <FILENAME>modmanager.cpp</FILENAME>
      <LINE>35</LINE>
      <COLUMN>45</COLUMN>
    </SFA>
    <DEFECTCODE>6276</DEFECTCODE>
    <DESCRIPTION>语义不同的字符串类型之间的强制转换: char * 转换为 wchar_t *。使用无效的字符串会导致未定义的行为。</DESCRIPTION>
    <FUNCTION>CWpnListMgr::HandleWindow</FUNCTION>
    <DECORATED>?HandleWindow@CWpnListMgr@@QAGJPAUHWND__@@IIJ@Z</DECORATED>
    <FUNCLINE>22</FUNCLINE>
    <PATH></PATH>
  </DEFECT>
</DEFECTS>